asyevent/__init__.py
asyevent/callback.py
asyevent/command.py
asyevent/event.py
asyevent/event_manager.py
asyevent/event_wrapper.py
asyevent/exceptions.py
asyevent-0.1.3.dist-info/LICENSE.rst
asyevent-0.1.3.dist-info/METADATA
asyevent-0.1.3.dist-info/WHEEL
asyevent-0.1.3.dist-info/top_level.txt
asyevent-0.1.3.dist-info/RECORD
