Metadata-Version: 2.1
Name: asyevent
Version: 0.1.3
Summary: An implementation of events and asynchronous callbacks using decorators.
Home-page: https://github.com/HerveZu/asyevent
Author: Zucchinetti Hervé
Author-email: herve.zucchinetti@gmail.com
License: MIT
Platform: UNKNOWN
Classifier: License :: OSI Approved :: MIT License
Classifier: Programming Language :: Python :: 3
Classifier: Programming Language :: Python :: 3.7
Classifier: Programming Language :: Python :: 3.8
Classifier: Programming Language :: Python :: 3.9
License-File: LICENSE.rst
Requires-Dist: asyncio
